metamart_source_cube/__init__.py
metamart_source_cube/adapters.py
metamart_source_cube/api.py
metamart_source_cube/base.py
metamart_source_cube/connector.py
metamart_source_cube/mock_tools.py
metamart_source_cube/package_definitions.py
metamart_source_cube/settings.py
metamart_source_cube/types.py
metamart_source_cube-0.0.2.dist-info/METADATA
metamart_source_cube-0.0.2.dist-info/WHEEL
metamart_source_cube-0.0.2.dist-info/RECORD
