Metadata-Version: 2.1
Name: metamart_source_cube
Version: 0.0.2
Summary: 
Home-page: https://www.metamart.io/
License: Elastic-2.0
Author: Metamart
Author-email: dev@metamart.io
Requires-Python: >=3.9.13,<4.0.0
Classifier: License :: Other/Proprietary License
Classifier: Programming Language :: Python :: 3
Classifier: Programming Language :: Python :: 3.10
Classifier: Programming Language :: Python :: 3.11
Classifier: Programming Language :: Python :: 3.12
Requires-Dist: metamart-schemas (>=0.2.6,<0.3.0)
Requires-Dist: multimethod (>=1.8,<2.0,!=1.11)
Requires-Dist: polyfactory (>=2.14.1,<3.0.0)
Requires-Dist: pydantic (>=1.9.1,<2.0.0)
Requires-Dist: pyjwt (>=2.8.0,<3.0.0)
Requires-Dist: python-dotenv (>=0.21.1,<0.22.0)
Project-URL: Documentation, https://docs.metamart.io/
Project-URL: Repository, https://github.com/meta-mart/metamart-core/tree/master/metamart-integrations/source-cube
